behave_bo/__init__.py
behave_bo/__main__.py
behave_bo/_types.py
behave_bo/capture.py
behave_bo/configuration.py
behave_bo/consts.py
behave_bo/coverage.py
behave_bo/enums.py
behave_bo/fixture.py
behave_bo/i18n.py
behave_bo/importer.py
behave_bo/log_capture.py
behave_bo/loggers.py
behave_bo/matchers.py
behave_bo/model.py
behave_bo/model_core.py
behave_bo/model_describe.py
behave_bo/parser.py
behave_bo/runner.py
behave_bo/runner_util.py
behave_bo/step_registry.py
behave_bo/tag_expression.py
behave_bo/textutil.py
behave_bo/userdata.py
behave_bo/behave_django_bo/__init__.py
behave_bo/behave_django_bo/base_runner.py
behave_bo/behave_django_bo/cache.py
behave_bo/behave_django_bo/client.py
behave_bo/behave_django_bo/consts.py
behave_bo/behave_django_bo/enums.py
behave_bo/behave_django_bo/environment.py
behave_bo/behave_django_bo/extractors.py
behave_bo/behave_django_bo/helpers.py
behave_bo/behave_django_bo/loggers.py
behave_bo/behave_django_bo/requests.py
behave_bo/behave_django_bo/runner.py
behave_bo/behave_django_bo/signals.py
behave_bo/behave_django_bo/testcase.py
behave_bo/behave_django_bo/utils.py
behave_bo/behave_django_bo/management/__init__.py
behave_bo/behave_django_bo/management/commands/__init__.py
behave_bo/behave_django_bo/management/commands/behave.py
behave_bo/behave_django_bo/management/commands/behave_export_html_report.py
behave_bo/behave_django_bo/plugins/__init__.py
behave_bo/behave_django_bo/plugins/base.py
behave_bo/behave_django_bo/plugins/override_settings.py
behave_bo/behave_django_bo/scripts/__init__.py
behave_bo/behave_django_bo/scripts/reuse_requests_factories.py
behave_bo/behave_django_bo/wrapper_with_queries_log/__init__.py
behave_bo/behave_django_bo/wrapper_with_queries_log/base.py
behave_bo/formatter/__init__.py
behave_bo/formatter/_builtins.py
behave_bo/formatter/_registry.py
behave_bo/formatter/ansi_escapes.py
behave_bo/formatter/base.py
behave_bo/formatter/json.py
behave_bo/formatter/null.py
behave_bo/formatter/plain.py
behave_bo-0.0.18.dist-info/METADATA
behave_bo-0.0.18.dist-info/WHEEL
behave_bo-0.0.18.dist-info/namespace_packages.txt
behave_bo-0.0.18.dist-info/top_level.txt
behave_bo-0.0.18.dist-info/RECORD
