Metadata-Version: 2.4
Name: behave_bo
Version: 0.0.18
Summary: Electronic Document Management
Home-page: http://docs.budg.bars.group/behave_bo/
Download-URL: 
Author: Stepan Lushchiy
Author-email: s.lushchiy@bars.group
Platform: Any
Classifier: Development Status :: 3 - Alpha
Classifier: License :: OSI Approved :: Apache Software License
Classifier: Programming Language :: Python
Classifier: Programming Language :: Python :: 3
Classifier: Programming Language :: Python :: 3.6
Classifier: Programming Language :: Python :: 3.7
Classifier: Programming Language :: Python :: 3.8
Classifier: Programming Language :: Python :: 3.9
Classifier: Intended Audience :: Developers
Classifier: Environment :: Web Environment
Requires-Dist: parse>=1.18.0
Requires-Dist: Django>=2.2.2
Requires-Dist: coverage==5.5
Requires-Dist: time-machine==2.16.0
Dynamic: author
Dynamic: author-email
Dynamic: classifier
Dynamic: description
Dynamic: home-page
Dynamic: platform
Dynamic: requires-dist
Dynamic: summary
